<?xml version="1.0" encoding="UTF-8" standalone="no"?>
<configuration version="2.0.0.12">
  <DisplayManager>
    <SystemInitScript/>
    <SystemStartScript/>
  </DisplayManager>
  <General>
    <HarmonyPath path="../../../../.."/>
    <Processor name="PIC32MZ2064DAB288"/>
    <Board name=""/>
    <ForceOptimization flag="true"/>
    <MergeStrategy flag="USER_ALL"/>
  </General>
  <Manifest>
    <Files>
      <File>
        <Name>osal_impl_basic.h</Name>
        <Path>Header Files/framework/osal/src</Path>
      </File>
      <File>
        <Name>drv_tmr_mapping.h</Name>
        <Path>Header Files/framework/driver/tmr</Path>
      </File>
      <File>
        <Name>drv_tmr_variant_mapping.h</Name>
        <Path>Header Files/framework/driver/tmr/src</Path>
      </File>
      <File>
        <Name>drv_tmr_local.h</Name>
        <Path>Header Files/framework/driver/tmr/src</Path>
      </File>
      <File>
        <Name>driver_common.h</Name>
        <Path>Header Files/framework/driver</Path>
      </File>
      <File>
        <Name>drv_tmr.h</Name>
        <Path>Header Files/framework/driver/tmr</Path>
      </File>
      <File>
        <Name>sys_devcon.c</Name>
        <Path>Source Files/framework/system/devcon/src</Path>
      </File>
      <File>
        <Name>sys_tmr.h</Name>
        <Path>Header Files/framework/system/tmr</Path>
      </File>
      <File>
        <Name>sys_tmr.c</Name>
        <Path>Source Files/framework/system/tmr/src</Path>
      </File>
      <File>
        <Name>osal.h</Name>
        <Path>Header Files/framework/osal</Path>
      </File>
      <File>
        <Name>sys_ports.h</Name>
        <Path>Header Files/framework/system/ports</Path>
      </File>
      <File>
        <Name>driver.h</Name>
        <Path>Header Files/framework/driver</Path>
      </File>
      <File>
        <Name>sys_devcon_cache.h</Name>
        <Path>Source Files/framework/system/devcon/src</Path>
      </File>
      <File>
        <Name>sys_common.h</Name>
        <Path>Header Files/framework/system/common</Path>
      </File>
      <File>
        <Name>sys_buffer.h</Name>
        <Path>Header Files/framework/system/common</Path>
      </File>
      <File>
        <Name>sys_int_pic32.c</Name>
        <Path>Source Files/framework/system/int/src</Path>
      </File>
      <File>
        <Name>sys_clk_compatibility.h</Name>
        <Path>Header Files/framework/system/clk</Path>
      </File>
      <File>
        <Name>sys_clk.h</Name>
        <Path>Header Files/framework/system/clk</Path>
      </File>
      <File>
        <Name>osal_impl_none.h</Name>
        <Path>Header Files/framework/osal/src</Path>
      </File>
      <File>
        <Name>sys_clk_mapping.h</Name>
        <Path>Header Files/framework/system/clk</Path>
      </File>
      <File>
        <Name>sys_devcon_cache_pic32mz.S</Name>
        <Path>Source Files/framework/system/devcon/src</Path>
      </File>
      <File>
        <Name>osal_definitions.h</Name>
        <Path>Header Files/framework/osal</Path>
      </File>
      <File>
        <Name>sys_int_mapping.h</Name>
        <Path>Header Files/framework/system/int</Path>
      </File>
      <File>
        <Name>drv_tmr.c</Name>
        <Path>Source Files/framework/driver/tmr/src/dynamic</Path>
      </File>
      <File>
        <Name>sys_int_private.h</Name>
        <Path>Header Files/framework/system/int/src</Path>
      </File>
      <File>
        <Name>sys_devcon.h</Name>
        <Path>Header Files/framework/system/devcon</Path>
      </File>
      <File>
        <Name>drv_tmr_compatibility.h</Name>
        <Path>Header Files/framework/driver/tmr</Path>
      </File>
      <File>
        <Name>sys_tmr_local.h</Name>
        <Path>Header Files/framework/system/tmr/src</Path>
      </File>
      <File>
        <Name>system.h</Name>
        <Path>Header Files/framework/system</Path>
      </File>
      <File>
        <Name>sys_debug.h</Name>
        <Path>Header Files/framework/system/debug</Path>
      </File>
      <File>
        <Name>sys_module.h</Name>
        <Path>Header Files/framework/system/common</Path>
      </File>
      <File>
        <Name>sys_devcon_pic32mz.c</Name>
        <Path>Source Files/framework/system/devcon/src</Path>
      </File>
      <File>
        <Name>sys_devcon_local.h</Name>
        <Path>Header Files/framework/system/devcon/src</Path>
      </File>
      <File>
        <Name>sys_queue.h</Name>
        <Path>Header Files/framework/system/common</Path>
      </File>
      <File>
        <Name>sys_int.h</Name>
        <Path>Header Files/framework/system/int</Path>
      </File>
    </Files>
    <Templates>
      <Template>
        <Name>main.c</Name>
        <Path>Source Files/app</Path>
      </Template>
      <Template>
        <Name>system_config.h</Name>
        <Path>Header Files/app/system_config/pic32mz_da_sk</Path>
        <Checksum>B904BE6AFA543D68DABB2C22B8BDFEE6</Checksum>
      </Template>
      <Template>
        <Name>system_init.c</Name>
        <Path>Source Files/app/system_config/pic32mz_da_sk</Path>
        <Checksum>801DB5F3FED7C63F755AF516713D2662</Checksum>
      </Template>
      <Template>
        <Name>sys_clk_static.c</Name>
        <Path>Source Files/app/system_config/pic32mz_da_sk/framework/system/clk/src</Path>
        <Checksum>5DEC6FBF578D0F2E0CFD7A4E273CFADC</Checksum>
      </Template>
      <Template>
        <Name>app.c</Name>
        <Path>Source Files/app</Path>
      </Template>
      <Template>
        <Name>bsp.h</Name>
        <Path>Header Files/app/system_config/pic32mz_da_sk/bsp</Path>
        <Checksum>018D32CE8E3A3DAB4E198AC0EF77984D</Checksum>
      </Template>
      <Template>
        <Name>system_exceptions.c</Name>
        <Path>Source Files/app/system_config/pic32mz_da_sk</Path>
        <Checksum>C111969CA43D6CEA1E9E33A6164E7AE0</Checksum>
      </Template>
      <Template>
        <Name>system_interrupt.c</Name>
        <Path>Source Files/app/system_config/pic32mz_da_sk</Path>
        <Checksum>C934CFD980878E57EE336D976F540A07</Checksum>
      </Template>
      <Template>
        <Name>sys_ports_static.c</Name>
        <Path>Source Files/app/system_config/pic32mz_da_sk/framework/system/ports/src</Path>
        <Checksum>3DFB0BC56732FDD6D5377CC83C754517</Checksum>
      </Template>
      <Template>
        <Name>system_definitions.h</Name>
        <Path>Header Files/app/system_config/pic32mz_da_sk</Path>
        <Checksum>6A6F409C1D8BE8FBFD0A697C13D906E3</Checksum>
      </Template>
      <Template>
        <Name>bsp.c</Name>
        <Path>Source Files/app/system_config/pic32mz_da_sk/bsp</Path>
        <Checksum>6D0961160B9CA04B50D20493874A5D26</Checksum>
      </Template>
      <Template>
        <Name>system_tasks.c</Name>
        <Path>Source Files/app/system_config/pic32mz_da_sk</Path>
        <Checksum>0F05C999623AAF5AD70B92AE90BB0C67</Checksum>
      </Template>
      <Template>
        <Name>app.h</Name>
        <Path>Header Files/app</Path>
      </Template>
    </Templates>
    <CompilerItems>
      <C32>
        <Include value="E:/official/git/core/apps/examples/peripheral/ports/blinky_leds/firmware/src"/>
        <Include value="E:/official/git/core/apps/examples/peripheral/ports/blinky_leds/firmware/src/system_config/pic32mz_da_sk"/>
        <Include value="E:/official/git/core/framework"/>
        <Include value="E:/official/git/core/apps/examples/peripheral/ports/blinky_leds/firmware/src/system_config/pic32mz_da_sk/framework"/>
        <Include value="../src/system_config/pic32mz_da_sk/bsp"/>
      </C32>
    </CompilerItems>
    <Libraries>
      <Library value="../../../../../../../bin/framework/peripheral/PIC32MZ2064DAB288_peripherals.a"/>
    </Libraries>
  </Manifest>
</configuration>
